setup.py
jettonpriceapi/__init__.py
jettonpriceapi/jetton.py
jettonpriceapi.egg-info/PKG-INFO
jettonpriceapi.egg-info/SOURCES.txt
jettonpriceapi.egg-info/dependency_links.txt
jettonpriceapi.egg-info/requires.txt
jettonpriceapi.egg-info/top_level.txt